mindtrace/apps/mindtrace/apps/__init__.py
mindtrace/automation/mindtrace/automation/__init__.py
mindtrace/automation/mindtrace/automation/label_studio/exceptions.py
mindtrace/automation/mindtrace/automation/label_studio/label_studio_api.py
mindtrace/automation/mindtrace/automation/utils/feature_classifier.py
mindtrace/automation/mindtrace/automation/utils/feature_detector.py
mindtrace/automation/mindtrace/automation/utils/feature_extractors.py
mindtrace/automation/mindtrace/automation/utils/feature_models.py
mindtrace/automation/mindtrace/automation/utils/generate_id_config.py
mindtrace/cluster/mindtrace/cluster/__init__.py
mindtrace/cluster/mindtrace/cluster/core/cluster.py
mindtrace/cluster/mindtrace/cluster/core/dlq.py
mindtrace/cluster/mindtrace/cluster/core/types.py
mindtrace/cluster/mindtrace/cluster/workers/echo_worker.py
mindtrace/cluster/mindtrace/cluster/workers/run_script_worker.py
mindtrace/cluster/mindtrace/cluster/workers/environments/docker_env.py
mindtrace/cluster/mindtrace/cluster/workers/environments/git_env.py
mindtrace/core/mindtrace/core/__init__.py
mindtrace/core/mindtrace/core/base/__init__.py
mindtrace/core/mindtrace/core/base/mindtrace_base.py
mindtrace/core/mindtrace/core/config/__init__.py
mindtrace/core/mindtrace/core/config/config.ini
mindtrace/core/mindtrace/core/config/config.py
mindtrace/core/mindtrace/core/logging/__init__.py
mindtrace/core/mindtrace/core/logging/logger.py
mindtrace/core/mindtrace/core/observables/context_listener.py
mindtrace/core/mindtrace/core/observables/event_bus.py
mindtrace/core/mindtrace/core/observables/observable_context.py
mindtrace/core/mindtrace/core/samples/echo_task.py
mindtrace/core/mindtrace/core/types/__init__.py
mindtrace/core/mindtrace/core/types/bounding_box.py
mindtrace/core/mindtrace/core/types/rotated_rect.py
mindtrace/core/mindtrace/core/types/task_schema.py
mindtrace/core/mindtrace/core/utils/__init__.py
mindtrace/core/mindtrace/core/utils/checks.py
mindtrace-0.8.0.dist-info/licenses/LICENSE
mindtrace-0.8.0.dist-info/METADATA
mindtrace-0.8.0.dist-info/WHEEL
mindtrace-0.8.0.dist-info/top_level.txt
mindtrace-0.8.0.dist-info/RECORD
