Metadata-Version: 2.4
Name: mindtrace
Version: 0.8.0
Summary: Mindtrace monorepo with modular packages
Author: Mindtrace Team
License-Expression: Apache-2.0
Project-URL: Homepage, https://mindtrace.ai
Project-URL: Repository, https://github.com/mindtrace/mindtrace
Classifier: Programming Language :: Python :: 3
Classifier: Programming Language :: Python :: 3.12
Requires-Python: >=3.12
License-File: LICENSE
Requires-Dist: mindtrace-core>=0.8.0
Requires-Dist: mindtrace-jobs>=0.8.0
Requires-Dist: mindtrace-registry>=0.8.0
Requires-Dist: mindtrace-database>=0.8.0
Requires-Dist: mindtrace-services>=0.8.0
Requires-Dist: mindtrace-hardware>=0.8.0
Requires-Dist: mindtrace-cluster>=0.8.0
Requires-Dist: mindtrace-models>=0.8.0
Requires-Dist: mindtrace-automation>=0.8.0
Requires-Dist: mindtrace-apps>=0.8.0
Requires-Dist: mindtrace-ui>=0.8.0
Requires-Dist: mindtrace-datalake>=0.8.0
Requires-Dist: mindtrace-storage>=0.8.0
Provides-Extra: cameras-basler
Requires-Dist: mindtrace-hardware[cameras-basler]>=0.8.0; extra == "cameras-basler"
Provides-Extra: cameras-genicam
Requires-Dist: mindtrace-hardware[cameras-genicam]>=0.8.0; extra == "cameras-genicam"
Provides-Extra: cameras-all
Requires-Dist: mindtrace-hardware[cameras-all]>=0.8.0; extra == "cameras-all"
Provides-Extra: stereo-basler
Requires-Dist: mindtrace-hardware[stereo-basler]>=0.8.0; extra == "stereo-basler"
Provides-Extra: stereo-all
Requires-Dist: mindtrace-hardware[stereo-all]>=0.8.0; extra == "stereo-all"
Provides-Extra: hardware-all
Requires-Dist: mindtrace-hardware[hardware-all]>=0.8.0; extra == "hardware-all"
Dynamic: license-file
